odoo9_addon_stock_picking_mass_assign-9.0.1.0.0.99.dev9-py3.8-nspkg.pth
odoo_addons/stock_picking_mass_assign/README.rst
odoo_addons/stock_picking_mass_assign/__init__.py
odoo_addons/stock_picking_mass_assign/__openerp__.py
odoo_addons/stock_picking_mass_assign/data/cron_data.xml
odoo_addons/stock_picking_mass_assign/i18n/de.po
odoo_addons/stock_picking_mass_assign/i18n/es.po
odoo_addons/stock_picking_mass_assign/i18n/fr.po
odoo_addons/stock_picking_mass_assign/i18n/it.po
odoo_addons/stock_picking_mass_assign/i18n/pt_BR.po
odoo_addons/stock_picking_mass_assign/i18n/sl.po
odoo_addons/stock_picking_mass_assign/i18n/stock_picking_mass_assign.pot
odoo_addons/stock_picking_mass_assign/models/__init__.py
odoo_addons/stock_picking_mass_assign/models/stock.py
odoo_addons/stock_picking_mass_assign/static/description/icon.png
odoo_addons/stock_picking_mass_assign/test/test_check_assign_all.yml
odoo_addons/stock_picking_mass_assign/wizard/__init__.py
odoo_addons/stock_picking_mass_assign/wizard/check_assign_all.py
odoo_addons/stock_picking_mass_assign/wizard/check_assign_all_view.xml
odoo9_addon_stock_picking_mass_assign-9.0.1.0.0.99.dev9.dist-info/METADATA
odoo9_addon_stock_picking_mass_assign-9.0.1.0.0.99.dev9.dist-info/WHEEL
odoo9_addon_stock_picking_mass_assign-9.0.1.0.0.99.dev9.dist-info/namespace_packages.txt
odoo9_addon_stock_picking_mass_assign-9.0.1.0.0.99.dev9.dist-info/top_level.txt
odoo9_addon_stock_picking_mass_assign-9.0.1.0.0.99.dev9.dist-info/RECORD
